gloss_rs-0.7.0.dist-info/METADATA
gloss_rs-0.7.0.dist-info/WHEEL
gloss/log.pyi
gloss/components.pyi
gloss/types.pyi
gloss/__pycache__/__init__.cpython-38.pyc
gloss/__init__.pyi
gloss/__init__.py
gloss/builders.pyi
gloss/gloss.abi3.so
gloss_rs-0.7.0.dist-info/RECORD
