Metadata-Version: 2.4
Name: gloss_rs
Version: 0.7.0
Summary: A light-weight Physically Based Renderer
Author: Radu Alexandru Rosu <alex@meshcapade.com>, Aman Shenoy <aman@meshcapade.com>
Author-email: Radu Alexandru Rosu <alex@meshcapade.com>, Aman Shenoy <aman@meshcapade.com>
License: MIT
Requires-Python: >=3.8
